LICENSE
MANIFEST.in
README.md
setup.cfg
setup.py
docassemble/__init__.py
docassemble.cladmin.egg-info/PKG-INFO
docassemble.cladmin.egg-info/SOURCES.txt
docassemble.cladmin.egg-info/dependency_links.txt
docassemble.cladmin.egg-info/namespace_packages.txt
docassemble.cladmin.egg-info/not-zip-safe
docassemble.cladmin.egg-info/requires.txt
docassemble.cladmin.egg-info/top_level.txt
docassemble/cladmin/__init__.py
docassemble/cladmin/data/questions/acknowledge-receipt.yml
docassemble/cladmin/data/questions/agent-appointment.yml
docassemble/cladmin/data/questions/authority.yml
docassemble/cladmin/data/questions/quote-letter-estate.yml
docassemble/cladmin/data/questions/quote-letter-general.yml
docassemble/cladmin/data/sources/README.md
docassemble/cladmin/data/static/README.md
docassemble/cladmin/data/templates/Acknowledgement_of_receipt_of_documents_form.docx
docassemble/cladmin/data/templates/Appointment_of_agent_form.docx
docassemble/cladmin/data/templates/Authority_to_act_form.docx
docassemble/cladmin/data/templates/README.md
docassemble/cladmin/data/templates/Scope_of_work_and_pricing_letter.docx
docassemble/cladmin/data/templates/Scope_of_work_and_pricing_letter_-_estate_planning.docx