Metadata-Version: 2.1
Name: docassemble.cladmin
Version: 0.0.1
Summary: A docassemble extension containing Chat Legal admin documents.
Home-page: https://docassemble.org
Author: System Administrator
Author-email: dqyhii9@gmail.com
License: The MIT License (MIT)
Platform: UNKNOWN
